basic_math_operations.cpython-310-x86_64-linux-gnu.so
src/python-module/libbasic_math_operations.a
src/python-module/version.txt
src/python-module/module.c
basic_math_operations-1.0.165.dist-info/METADATA
basic_math_operations-1.0.165.dist-info/LICENSE
basic_math_operations-1.0.165.dist-info/WHEEL
basic_math_operations-1.0.165.dist-info/top_level.txt
basic_math_operations-1.0.165.dist-info/RECORD
basic_math_operations-1.0.165.data/data/src/python-module/libbasic_math_operations.a
basic_math_operations-1.0.165.data/data/src/python-module/version.txt
